unanimous/__init__.py
unanimous/__main__.py
unanimous/custom_nonwords.py
unanimous/pypi_load.py
unanimous/store.py
unanimous/util.py
unanimous/version.py
unanimous/filters/__init__.py
unanimous/filters/nonwords.py
unanimous-0.8.4.dist-info/METADATA
unanimous-0.8.4.dist-info/WHEEL
unanimous-0.8.4.dist-info/top_level.txt
unanimous-0.8.4.dist-info/RECORD
