Metadata-Version: 2.1
Name: unanimous
Version: 0.8.4
Summary: Extension to make running pyspelling in CI easier. Maintains a common word exception list of technical terms so that every project does not need to exclude words like PyPi and GitHub etc..
Home-page: https://github.com/resplendent-dev/unanimous
Author: Tim Gates
Author-email: tim.gates@iress.com
Maintainer: Tim Gates
Maintainer-email: tim.gates@iress.com
License: GPLv3+
Classifier: Development Status :: 4 - Beta
Classifier: Programming Language :: Python
Classifier: Programming Language :: Python :: 3
Classifier: Programming Language :: Python :: 3.7
Classifier: Programming Language :: Python :: 3.8
Classifier: Programming Language :: Python :: Implementation :: CPython
Classifier: Programming Language :: Python :: Implementation :: PyPy
Classifier: Operating System :: OS Independent
Classifier: License :: OSI Approved :: GNU General Public License v3 (GPLv3)
Requires-Python: >=3.7
Requires-Dist: pyspelling
Requires-Dist: dataset
Requires-Dist: requests
Requires-Dist: click
Requires-Dist: defusedxml
Requires-Dist: backoff
Requires-Dist: setuptools >65.5.1
